{"nodes": [{"id": "players_career_summary", "label": "CareerSummary", "file_type": "code", "source_file": "src/components/players/career-summary.tsx", "source_location": null, "source_url": null, "captured_at": null, "author": null, "contributor": null}, {"id": "concept_career_engine", "label": "Career engine / tier progression", "file_type": "concept", "source_file": "src/components/players/career-summary.tsx", "source_location": null, "source_url": null, "captured_at": null, "author": null, "contributor": null}], "edges": [{"source": "players_career_summary", "target": "players_player_card", "relation": "references", "confidence": "EXTRACTED", "confidence_score": 1.0, "source_file": "src/components/players/career-summary.tsx", "source_location": null, "weight": 1.0}, {"source": "players_career_summary", "target": "lib_player_career_bestpositionfromoverall", "relation": "calls", "confidence": "EXTRACTED", "confidence_score": 1.0, "source_file": "src/components/players/career-summary.tsx", "source_location": null, "weight": 1.0}, {"source": "players_career_summary", "target": "lib_player_career_computewinrate", "relation": "calls", "confidence": "EXTRACTED", "confidence_score": 1.0, "source_file": "src/components/players/career-summary.tsx", "source_location": null, "weight": 1.0}, {"source": "players_career_summary", "target": "lib_player_position_positionabbreviation", "relation": "calls", "confidence": "EXTRACTED", "confidence_score": 1.0, "source_file": "src/components/players/career-summary.tsx", "source_location": null, "weight": 1.0}, {"source": "players_career_summary", "target": "concept_career_engine", "relation": "implements", "confidence": "INFERRED", "confidence_score": 0.85, "source_file": "src/components/players/career-summary.tsx", "source_location": null, "weight": 1.0}], "hyperedges": [{"id": "he_career_presentation", "label": "Career presentation composition (card + summary + tier)", "nodes": ["players_career_summary", "players_player_card", "concept_career_engine"], "relation": "participate_in", "confidence": "INFERRED", "confidence_score": 0.75, "source_file": "src/components/players/career-summary.tsx"}]}